{
  "items": [
    {
      "id": "003-item-00",
      "filename": "003_00_00_开场.mp3",
      "filepath": "/audios/single/003_00_00_开场.mp3",
      "date": "2026年3月5日",
      "startTime": "00:00:09.97",
      "endTime": "00:13:35.23",
      "personTag": "开场",
      "lastPosition": 0,
      "subtitleJsonPath": "/home/duino/ws/ququ/process_youtube/data/03_transcripts/曲曲2026/003 - 曲曲現場直播 2026年3月5日 ｜ 曲曲麥肯錫/00_开场.json"
    },
    {
      "id": "003-item-01",
      "filename": "003_01_01_25岁常春藤硕士_连麦.mp3",
      "filepath": "/audios/single/003_01_01_25岁常春藤硕士_连麦.mp3",
      "date": "2026年3月5日",
      "startTime": "00:13:35.23",
      "endTime": "00:29:32.86",
      "personTag": "25岁常春藤硕士",
      "lastPosition": 0,
      "subtitleJsonPath": "/home/duino/ws/ququ/process_youtube/data/03_transcripts/曲曲2026/003 - 曲曲現場直播 2026年3月5日 ｜ 曲曲麥肯錫/01_25岁常春藤硕士_连麦.json"
    },
    {
      "id": "003-item-02",
      "filename": "003_02_02_25岁常春藤硕士_评论.mp3",
      "filepath": "/audios/single/003_02_02_25岁常春藤硕士_评论.mp3",
      "date": "2026年3月5日",
      "startTime": "00:29:32.86",
      "endTime": "00:33:29.60",
      "personTag": "25岁常春藤硕士",
      "lastPosition": 0,
      "subtitleJsonPath": "/home/duino/ws/ququ/process_youtube/data/03_transcripts/曲曲2026/003 - 曲曲現場直播 2026年3月5日 ｜ 曲曲麥肯錫/02_25岁常春藤硕士_评论.json"
    },
    {
      "id": "003-item-03",
      "filename": "003_03_03_25岁国企女生_连麦.mp3",
      "filepath": "/audios/single/003_03_03_25岁国企女生_连麦.mp3",
      "date": "2026年3月5日",
      "startTime": "00:33:29.60",
      "endTime": "00:45:32.72",
      "personTag": "25岁国企女生",
      "lastPosition": 0,
      "subtitleJsonPath": "/home/duino/ws/ququ/process_youtube/data/03_transcripts/曲曲2026/003 - 曲曲現場直播 2026年3月5日 ｜ 曲曲麥肯錫/03_25岁国企女生_连麦.json"
    },
    {
      "id": "003-item-04",
      "filename": "003_04_04_25岁国企女生_评论.mp3",
      "filepath": "/audios/single/003_04_04_25岁国企女生_评论.mp3",
      "date": "2026年3月5日",
      "startTime": "00:45:32.72",
      "endTime": "01:00:31.16",
      "personTag": "25岁国企女生",
      "lastPosition": 0,
      "subtitleJsonPath": "/home/duino/ws/ququ/process_youtube/data/03_transcripts/曲曲2026/003 - 曲曲現場直播 2026年3月5日 ｜ 曲曲麥肯錫/04_25岁国企女生_评论.json"
    },
    {
      "id": "003-item-05",
      "filename": "003_05_05_26岁二胎宝妈_连麦.mp3",
      "filepath": "/audios/single/003_05_05_26岁二胎宝妈_连麦.mp3",
      "date": "2026年3月5日",
      "startTime": "01:00:31.16",
      "endTime": "01:12:56.63",
      "personTag": "26岁二胎宝妈",
      "lastPosition": 0,
      "subtitleJsonPath": "/home/duino/ws/ququ/process_youtube/data/03_transcripts/曲曲2026/003 - 曲曲現場直播 2026年3月5日 ｜ 曲曲麥肯錫/05_26岁二胎宝妈_连麦.json"
    },
    {
      "id": "003-item-06",
      "filename": "003_06_06_26岁二胎宝妈_评论.mp3",
      "filepath": "/audios/single/003_06_06_26岁二胎宝妈_评论.mp3",
      "date": "2026年3月5日",
      "startTime": "01:12:56.63",
      "endTime": "01:23:12.60",
      "personTag": "26岁二胎宝妈",
      "lastPosition": 0,
      "subtitleJsonPath": "/home/duino/ws/ququ/process_youtube/data/03_transcripts/曲曲2026/003 - 曲曲現場直播 2026年3月5日 ｜ 曲曲麥肯錫/06_26岁二胎宝妈_评论.json"
    },
    {
      "id": "003-item-07",
      "filename": "003_07_07_33岁私域电商_连麦.mp3",
      "filepath": "/audios/single/003_07_07_33岁私域电商_连麦.mp3",
      "date": "2026年3月5日",
      "startTime": "01:23:12.60",
      "endTime": "01:34:30.72",
      "personTag": "33岁私域电商",
      "lastPosition": 0,
      "subtitleJsonPath": "/home/duino/ws/ququ/process_youtube/data/03_transcripts/曲曲2026/003 - 曲曲現場直播 2026年3月5日 ｜ 曲曲麥肯錫/07_33岁私域电商_连麦.json"
    },
    {
      "id": "003-item-08",
      "filename": "003_08_08_33岁私域电商_评论.mp3",
      "filepath": "/audios/single/003_08_08_33岁私域电商_评论.mp3",
      "date": "2026年3月5日",
      "startTime": "01:34:30.72",
      "endTime": "01:42:45.61",
      "personTag": "33岁私域电商",
      "lastPosition": 0,
      "subtitleJsonPath": "/home/duino/ws/ququ/process_youtube/data/03_transcripts/曲曲2026/003 - 曲曲現場直播 2026年3月5日 ｜ 曲曲麥肯錫/08_33岁私域电商_评论.json"
    },
    {
      "id": "003-item-09",
      "filename": "003_09_09_23岁夜场女生_连麦.mp3",
      "filepath": "/audios/single/003_09_09_23岁夜场女生_连麦.mp3",
      "date": "2026年3月5日",
      "startTime": "01:42:45.61",
      "endTime": "01:56:52.42",
      "personTag": "23岁夜场女生",
      "lastPosition": 0,
      "subtitleJsonPath": "/home/duino/ws/ququ/process_youtube/data/03_transcripts/曲曲2026/003 - 曲曲現場直播 2026年3月5日 ｜ 曲曲麥肯錫/09_23岁夜场女生_连麦.json"
    },
    {
      "id": "003-item-10",
      "filename": "003_10_10_23岁夜场女生_评论.mp3",
      "filepath": "/audios/single/003_10_10_23岁夜场女生_评论.mp3",
      "date": "2026年3月5日",
      "startTime": "01:56:52.42",
      "endTime": "02:01:38.46",
      "personTag": "23岁夜场女生",
      "lastPosition": 0,
      "subtitleJsonPath": "/home/duino/ws/ququ/process_youtube/data/03_transcripts/曲曲2026/003 - 曲曲現場直播 2026年3月5日 ｜ 曲曲麥肯錫/10_23岁夜场女生_评论.json"
    },
    {
      "id": "003-item-11",
      "filename": "003_11_11_30岁金融女生_连麦.mp3",
      "filepath": "/audios/single/003_11_11_30岁金融女生_连麦.mp3",
      "date": "2026年3月5日",
      "startTime": "02:01:38.46",
      "endTime": "02:17:38.65",
      "personTag": "30岁金融女生",
      "lastPosition": 0,
      "subtitleJsonPath": "/home/duino/ws/ququ/process_youtube/data/03_transcripts/曲曲2026/003 - 曲曲現場直播 2026年3月5日 ｜ 曲曲麥肯錫/11_30岁金融女生_连麦.json"
    },
    {
      "id": "003-item-12",
      "filename": "003_12_12_30岁金融女生_评论.mp3",
      "filepath": "/audios/single/003_12_12_30岁金融女生_评论.mp3",
      "date": "2026年3月5日",
      "startTime": "02:17:38.65",
      "endTime": "02:30:23.60",
      "personTag": "30岁金融女生",
      "lastPosition": 0,
      "subtitleJsonPath": "/home/duino/ws/ququ/process_youtube/data/03_transcripts/曲曲2026/003 - 曲曲現場直播 2026年3月5日 ｜ 曲曲麥肯錫/12_30岁金融女生_评论.json"
    },
    {
      "id": "003-item-13",
      "filename": "003_13_13_28岁QS硕士_连麦.mp3",
      "filepath": "/audios/single/003_13_13_28岁QS硕士_连麦.mp3",
      "date": "2026年3月5日",
      "startTime": "02:30:23.60",
      "endTime": "02:46:06.64",
      "personTag": "28岁QS硕士",
      "lastPosition": 0,
      "subtitleJsonPath": "/home/duino/ws/ququ/process_youtube/data/03_transcripts/曲曲2026/003 - 曲曲現場直播 2026年3月5日 ｜ 曲曲麥肯錫/13_28岁QS硕士_连麦.json"
    },
    {
      "id": "003-item-14",
      "filename": "003_14_14_28岁QS硕士_评论.mp3",
      "filepath": "/audios/single/003_14_14_28岁QS硕士_评论.mp3",
      "date": "2026年3月5日",
      "startTime": "02:46:06.64",
      "endTime": "02:52:56.82",
      "personTag": "28岁QS硕士",
      "lastPosition": 0,
      "subtitleJsonPath": "/home/duino/ws/ququ/process_youtube/data/03_transcripts/曲曲2026/003 - 曲曲現場直播 2026年3月5日 ｜ 曲曲麥肯錫/14_28岁QS硕士_评论.json"
    },
    {
      "id": "003-item-15",
      "filename": "003_15_15_32岁单亲妈妈_连麦.mp3",
      "filepath": "/audios/single/003_15_15_32岁单亲妈妈_连麦.mp3",
      "date": "2026年3月5日",
      "startTime": "02:52:56.82",
      "endTime": "03:03:18.46",
      "personTag": "32岁单亲妈妈",
      "lastPosition": 0,
      "subtitleJsonPath": "/home/duino/ws/ququ/process_youtube/data/03_transcripts/曲曲2026/003 - 曲曲現場直播 2026年3月5日 ｜ 曲曲麥肯錫/15_32岁单亲妈妈_连麦.json"
    },
    {
      "id": "003-item-16",
      "filename": "003_16_16_32岁单亲妈妈_评论.mp3",
      "filepath": "/audios/single/003_16_16_32岁单亲妈妈_评论.mp3",
      "date": "2026年3月5日",
      "startTime": "03:03:18.46",
      "endTime": "03:11:31.98",
      "personTag": "32岁单亲妈妈",
      "lastPosition": 0,
      "subtitleJsonPath": "/home/duino/ws/ququ/process_youtube/data/03_transcripts/曲曲2026/003 - 曲曲現場直播 2026年3月5日 ｜ 曲曲麥肯錫/16_32岁单亲妈妈_评论.json"
    },
    {
      "id": "003-item-17",
      "filename": "003_17_17_30岁带货博主_连麦.mp3",
      "filepath": "/audios/single/003_17_17_30岁带货博主_连麦.mp3",
      "date": "2026年3月5日",
      "startTime": "03:11:31.98",
      "endTime": "03:27:30.12",
      "personTag": "30岁带货博主",
      "lastPosition": 0,
      "subtitleJsonPath": "/home/duino/ws/ququ/process_youtube/data/03_transcripts/曲曲2026/003 - 曲曲現場直播 2026年3月5日 ｜ 曲曲麥肯錫/17_30岁带货博主_连麦.json"
    },
    {
      "id": "003-item-18",
      "filename": "003_18_18_30岁带货博主_评论.mp3",
      "filepath": "/audios/single/003_18_18_30岁带货博主_评论.mp3",
      "date": "2026年3月5日",
      "startTime": "03:27:30.12",
      "endTime": "03:37:30.99",
      "personTag": "30岁带货博主",
      "lastPosition": 0,
      "subtitleJsonPath": "/home/duino/ws/ququ/process_youtube/data/03_transcripts/曲曲2026/003 - 曲曲現場直播 2026年3月5日 ｜ 曲曲麥肯錫/18_30岁带货博主_评论.json"
    },
    {
      "id": "003-item-19",
      "filename": "003_19_19_28岁英国博士_连麦.mp3",
      "filepath": "/audios/single/003_19_19_28岁英国博士_连麦.mp3",
      "date": "2026年3月5日",
      "startTime": "03:37:30.99",
      "endTime": "03:46:08.31",
      "personTag": "28岁英国博士",
      "lastPosition": 0,
      "subtitleJsonPath": "/home/duino/ws/ququ/process_youtube/data/03_transcripts/曲曲2026/003 - 曲曲現場直播 2026年3月5日 ｜ 曲曲麥肯錫/19_28岁英国博士_连麦.json"
    },
    {
      "id": "003-item-20",
      "filename": "003_20_20_28岁英国博士_评论.mp3",
      "filepath": "/audios/single/003_20_20_28岁英国博士_评论.mp3",
      "date": "2026年3月5日",
      "startTime": "03:46:08.31",
      "endTime": "03:49:57.95",
      "personTag": "28岁英国博士",
      "lastPosition": 0,
      "subtitleJsonPath": "/home/duino/ws/ququ/process_youtube/data/03_transcripts/曲曲2026/003 - 曲曲現場直播 2026年3月5日 ｜ 曲曲麥肯錫/20_28岁英国博士_评论.json"
    },
    {
      "id": "003-item-21",
      "filename": "003_21_21_26岁体制内_连麦.mp3",
      "filepath": "/audios/single/003_21_21_26岁体制内_连麦.mp3",
      "date": "2026年3月5日",
      "startTime": "03:49:57.95",
      "endTime": "04:03:06.52",
      "personTag": "26岁体制内",
      "lastPosition": 0,
      "subtitleJsonPath": "/home/duino/ws/ququ/process_youtube/data/03_transcripts/曲曲2026/003 - 曲曲現場直播 2026年3月5日 ｜ 曲曲麥肯錫/21_26岁体制内_连麦.json"
    },
    {
      "id": "003-item-22",
      "filename": "003_22_22_26岁体制内_评论.mp3",
      "filepath": "/audios/single/003_22_22_26岁体制内_评论.mp3",
      "date": "2026年3月5日",
      "startTime": "04:03:06.52",
      "endTime": "04:06:08.56",
      "personTag": "26岁体制内",
      "lastPosition": 0,
      "subtitleJsonPath": "/home/duino/ws/ququ/process_youtube/data/03_transcripts/曲曲2026/003 - 曲曲現場直播 2026年3月5日 ｜ 曲曲麥肯錫/22_26岁体制内_评论.json"
    },
    {
      "id": "002-item-00",
      "filename": "002_00_00_开场.mp3",
      "filepath": "/audios/single/002_00_00_开场.mp3",
      "date": "2026年3月6日",
      "startTime": "00:00:34.35",
      "endTime": "00:15:04.06",
      "personTag": "开场",
      "lastPosition": 0,
      "subtitleJsonPath": "/home/duino/ws/ququ/process_youtube/data/03_transcripts/曲曲2026/002 - 曲曲現場直播 2026年3月6日 ｜ 曲曲麥肯錫/00_开场.json"
    },
    {
      "id": "002-item-01",
      "filename": "002_01_01_25岁硕士沪漂职场副业_连麦.mp3",
      "filepath": "/audios/single/002_01_01_25岁硕士沪漂职场副业_连麦.mp3",
      "date": "2026年3月6日",
      "startTime": "00:15:04.06",
      "endTime": "00:26:56.86",
      "personTag": "25岁硕士沪漂职场副业",
      "lastPosition": 0,
      "subtitleJsonPath": "/home/duino/ws/ququ/process_youtube/data/03_transcripts/曲曲2026/002 - 曲曲現場直播 2026年3月6日 ｜ 曲曲麥肯錫/01_25岁硕士沪漂职场副业_连麦.json"
    },
    {
      "id": "002-item-02",
      "filename": "002_02_02_25岁硕士沪漂职场副业_评论.mp3",
      "filepath": "/audios/single/002_02_02_25岁硕士沪漂职场副业_评论.mp3",
      "date": "2026年3月6日",
      "startTime": "00:26:56.44",
      "endTime": "00:31:00.18",
      "personTag": "25岁硕士沪漂职场副业",
      "lastPosition": 0,
      "subtitleJsonPath": "/home/duino/ws/ququ/process_youtube/data/03_transcripts/曲曲2026/002 - 曲曲現場直播 2026年3月6日 ｜ 曲曲麥肯錫/02_25岁硕士沪漂职场副业_评论.json"
    },
    {
      "id": "002-item-03",
      "filename": "002_03_03_22岁老师婚恋策略困惑_连麦.mp3",
      "filepath": "/audios/single/002_03_03_22岁老师婚恋策略困惑_连麦.mp3",
      "date": "2026年3月6日",
      "startTime": "00:31:00.18",
      "endTime": "00:37:25.10",
      "personTag": "22岁老师婚恋策略困惑",
      "lastPosition": 0,
      "subtitleJsonPath": "/home/duino/ws/ququ/process_youtube/data/03_transcripts/曲曲2026/002 - 曲曲現場直播 2026年3月6日 ｜ 曲曲麥肯錫/03_22岁老师婚恋策略困惑_连麦.json"
    },
    {
      "id": "002-item-04",
      "filename": "002_04_04_22岁老师婚恋策略困惑_评论.mp3",
      "filepath": "/audios/single/002_04_04_22岁老师婚恋策略困惑_评论.mp3",
      "date": "2026年3月6日",
      "startTime": "00:37:22.29",
      "endTime": "00:39:46.14",
      "personTag": "22岁老师婚恋策略困惑",
      "lastPosition": 0,
      "subtitleJsonPath": "/home/duino/ws/ququ/process_youtube/data/03_transcripts/曲曲2026/002 - 曲曲現場直播 2026年3月6日 ｜ 曲曲麥肯錫/04_22岁老师婚恋策略困惑_评论.json"
    },
    {
      "id": "002-item-05",
      "filename": "002_05_05_25岁创业女生择城_连麦.mp3",
      "filepath": "/audios/single/002_05_05_25岁创业女生择城_连麦.mp3",
      "date": "2026年3月6日",
      "startTime": "00:39:47.16",
      "endTime": "01:01:04.63",
      "personTag": "25岁创业女生择城",
      "lastPosition": 0,
      "subtitleJsonPath": "/home/duino/ws/ququ/process_youtube/data/03_transcripts/曲曲2026/002 - 曲曲現場直播 2026年3月6日 ｜ 曲曲麥肯錫/05_25岁创业女生择城_连麦.json"
    },
    {
      "id": "002-item-06",
      "filename": "002_06_06_25岁创业女生择城_评论.mp3",
      "filepath": "/audios/single/002_06_06_25岁创业女生择城_评论.mp3",
      "date": "2026年3月6日",
      "startTime": "01:01:04.33",
      "endTime": "01:03:08.33",
      "personTag": "25岁创业女生择城",
      "lastPosition": 0,
      "subtitleJsonPath": "/home/duino/ws/ququ/process_youtube/data/03_transcripts/曲曲2026/002 - 曲曲現場直播 2026年3月6日 ｜ 曲曲麥肯錫/06_25岁创业女生择城_评论.json"
    },
    {
      "id": "002-item-07",
      "filename": "002_07_07_26岁老师转型焦虑_连麦.mp3",
      "filepath": "/audios/single/002_07_07_26岁老师转型焦虑_连麦.mp3",
      "date": "2026年3月6日",
      "startTime": "01:03:10.21",
      "endTime": "01:15:53.68",
      "personTag": "26岁老师转型焦虑",
      "lastPosition": 0,
      "subtitleJsonPath": "/home/duino/ws/ququ/process_youtube/data/03_transcripts/曲曲2026/002 - 曲曲現場直播 2026年3月6日 ｜ 曲曲麥肯錫/07_26岁老师转型焦虑_连麦.json"
    },
    {
      "id": "002-item-08",
      "filename": "002_08_08_26岁老师转型焦虑_评论.mp3",
      "filepath": "/audios/single/002_08_08_26岁老师转型焦虑_评论.mp3",
      "date": "2026年3月6日",
      "startTime": "01:15:51.45",
      "endTime": "01:16:24.11",
      "personTag": "26岁老师转型焦虑",
      "lastPosition": 0,
      "subtitleJsonPath": "/home/duino/ws/ququ/process_youtube/data/03_transcripts/曲曲2026/002 - 曲曲現場直播 2026年3月6日 ｜ 曲曲麥肯錫/08_26岁老师转型焦虑_评论.json"
    },
    {
      "id": "002-item-09",
      "filename": "002_09_09_销售岗关系内耗_连麦.mp3",
      "filepath": "/audios/single/002_09_09_销售岗关系内耗_连麦.mp3",
      "date": "2026年3月6日",
      "startTime": "01:16:24.11",
      "endTime": "01:30:13.65",
      "personTag": "销售岗关系内耗",
      "lastPosition": 0,
      "subtitleJsonPath": "/home/duino/ws/ququ/process_youtube/data/03_transcripts/曲曲2026/002 - 曲曲現場直播 2026年3月6日 ｜ 曲曲麥肯錫/09_销售岗关系内耗_连麦.json"
    },
    {
      "id": "002-item-10",
      "filename": "002_10_10_销售岗关系内耗_评论.mp3",
      "filepath": "/audios/single/002_10_10_销售岗关系内耗_评论.mp3",
      "date": "2026年3月6日",
      "startTime": "01:30:13.24",
      "endTime": "01:36:55.33",
      "personTag": "销售岗关系内耗",
      "lastPosition": 0,
      "subtitleJsonPath": "/home/duino/ws/ququ/process_youtube/data/03_transcripts/曲曲2026/002 - 曲曲現場直播 2026年3月6日 ｜ 曲曲麥肯錫/10_销售岗关系内耗_评论.json"
    },
    {
      "id": "002-item-11",
      "filename": "002_11_11_27岁本科老师内容变现_连麦.mp3",
      "filepath": "/audios/single/002_11_11_27岁本科老师内容变现_连麦.mp3",
      "date": "2026年3月6日",
      "startTime": "01:36:55.33",
      "endTime": "01:52:02.57",
      "personTag": "27岁本科老师内容变现",
      "lastPosition": 0,
      "subtitleJsonPath": "/home/duino/ws/ququ/process_youtube/data/03_transcripts/曲曲2026/002 - 曲曲現場直播 2026年3月6日 ｜ 曲曲麥肯錫/11_27岁本科老师内容变现_连麦.json"
    },
    {
      "id": "002-item-12",
      "filename": "002_12_12_27岁本科老师内容变现_评论.mp3",
      "filepath": "/audios/single/002_12_12_27岁本科老师内容变现_评论.mp3",
      "date": "2026年3月6日",
      "startTime": "01:52:02.47",
      "endTime": "02:01:35.66",
      "personTag": "27岁本科老师内容变现",
      "lastPosition": 0,
      "subtitleJsonPath": "/home/duino/ws/ququ/process_youtube/data/03_transcripts/曲曲2026/002 - 曲曲現場直播 2026年3月6日 ｜ 曲曲麥肯錫/12_27岁本科老师内容变现_评论.json"
    },
    {
      "id": "002-item-13",
      "filename": "002_13_13_29岁婚恋与家庭冲突_连麦.mp3",
      "filepath": "/audios/single/002_13_13_29岁婚恋与家庭冲突_连麦.mp3",
      "date": "2026年3月6日",
      "startTime": "02:01:35.66",
      "endTime": "02:15:41.49",
      "personTag": "29岁婚恋与家庭冲突",
      "lastPosition": 0,
      "subtitleJsonPath": "/home/duino/ws/ququ/process_youtube/data/03_transcripts/曲曲2026/002 - 曲曲現場直播 2026年3月6日 ｜ 曲曲麥肯錫/13_29岁婚恋与家庭冲突_连麦.json"
    },
    {
      "id": "002-item-14",
      "filename": "002_14_14_29岁婚恋与家庭冲突_评论.mp3",
      "filepath": "/audios/single/002_14_14_29岁婚恋与家庭冲突_评论.mp3",
      "date": "2026年3月6日",
      "startTime": "02:15:41.15",
      "endTime": "02:26:28.93",
      "personTag": "29岁婚恋与家庭冲突",
      "lastPosition": 0,
      "subtitleJsonPath": "/home/duino/ws/ququ/process_youtube/data/03_transcripts/曲曲2026/002 - 曲曲現場直播 2026年3月6日 ｜ 曲曲麥肯錫/14_29岁婚恋与家庭冲突_评论.json"
    },
    {
      "id": "002-item-15",
      "filename": "002_15_15_23岁在校女生对对碰_连麦.mp3",
      "filepath": "/audios/single/002_15_15_23岁在校女生对对碰_连麦.mp3",
      "date": "2026年3月6日",
      "startTime": "02:26:28.93",
      "endTime": "02:30:24.31",
      "personTag": "23岁在校女生对对碰",
      "lastPosition": 0,
      "subtitleJsonPath": "/home/duino/ws/ququ/process_youtube/data/03_transcripts/曲曲2026/002 - 曲曲現場直播 2026年3月6日 ｜ 曲曲麥肯錫/15_23岁在校女生对对碰_连麦.json"
    },
    {
      "id": "002-item-16",
      "filename": "002_16_16_23岁在校女生对对碰_评论.mp3",
      "filepath": "/audios/single/002_16_16_23岁在校女生对对碰_评论.mp3",
      "date": "2026年3月6日",
      "startTime": "02:30:23.99",
      "endTime": "02:30:54.05",
      "personTag": "23岁在校女生对对碰",
      "lastPosition": 0,
      "subtitleJsonPath": "/home/duino/ws/ququ/process_youtube/data/03_transcripts/曲曲2026/002 - 曲曲現場直播 2026年3月6日 ｜ 曲曲麥肯錫/16_23岁在校女生对对碰_评论.json"
    },
    {
      "id": "002-item-17",
      "filename": "002_17_17_女观众证书与就业焦虑_连麦.mp3",
      "filepath": "/audios/single/002_17_17_女观众证书与就业焦虑_连麦.mp3",
      "date": "2026年3月6日",
      "startTime": "02:30:54.05",
      "endTime": "02:34:58.27",
      "personTag": "女观众证书与就业焦虑",
      "lastPosition": 0,
      "subtitleJsonPath": "/home/duino/ws/ququ/process_youtube/data/03_transcripts/曲曲2026/002 - 曲曲現場直播 2026年3月6日 ｜ 曲曲麥肯錫/17_女观众证书与就业焦虑_连麦.json"
    },
    {
      "id": "002-item-18",
      "filename": "002_18_18_女观众证书与就业焦虑_评论.mp3",
      "filepath": "/audios/single/002_18_18_女观众证书与就业焦虑_评论.mp3",
      "date": "2026年3月6日",
      "startTime": "02:34:55.33",
      "endTime": "02:35:27.93",
      "personTag": "女观众证书与就业焦虑",
      "lastPosition": 0,
      "subtitleJsonPath": "/home/duino/ws/ququ/process_youtube/data/03_transcripts/曲曲2026/002 - 曲曲現場直播 2026年3月6日 ｜ 曲曲麥肯錫/18_女观众证书与就业焦虑_评论.json"
    },
    {
      "id": "002-item-19",
      "filename": "002_19_19_27岁本科产品虚荣消费_连麦.mp3",
      "filepath": "/audios/single/002_19_19_27岁本科产品虚荣消费_连麦.mp3",
      "date": "2026年3月6日",
      "startTime": "02:35:27.93",
      "endTime": "02:45:18.27",
      "personTag": "27岁本科产品虚荣消费",
      "lastPosition": 0,
      "subtitleJsonPath": "/home/duino/ws/ququ/process_youtube/data/03_transcripts/曲曲2026/002 - 曲曲現場直播 2026年3月6日 ｜ 曲曲麥肯錫/19_27岁本科产品虚荣消费_连麦.json"
    },
    {
      "id": "002-item-20",
      "filename": "002_20_20_27岁本科产品虚荣消费_评论.mp3",
      "filepath": "/audios/single/002_20_20_27岁本科产品虚荣消费_评论.mp3",
      "date": "2026年3月6日",
      "startTime": "02:45:15.94",
      "endTime": "02:50:10.84",
      "personTag": "27岁本科产品虚荣消费",
      "lastPosition": 0,
      "subtitleJsonPath": "/home/duino/ws/ququ/process_youtube/data/03_transcripts/曲曲2026/002 - 曲曲現場直播 2026年3月6日 ｜ 曲曲麥肯錫/20_27岁本科产品虚荣消费_评论.json"
    },
    {
      "id": "002-item-21",
      "filename": "002_21_21_观众关系纠纷止损_连麦.mp3",
      "filepath": "/audios/single/002_21_21_观众关系纠纷止损_连麦.mp3",
      "date": "2026年3月6日",
      "startTime": "02:50:10.84",
      "endTime": "03:00:30.92",
      "personTag": "观众关系纠纷止损",
      "lastPosition": 0,
      "subtitleJsonPath": "/home/duino/ws/ququ/process_youtube/data/03_transcripts/曲曲2026/002 - 曲曲現場直播 2026年3月6日 ｜ 曲曲麥肯錫/21_观众关系纠纷止损_连麦.json"
    },
    {
      "id": "002-item-22",
      "filename": "002_22_22_观众关系纠纷止损_评论.mp3",
      "filepath": "/audios/single/002_22_22_观众关系纠纷止损_评论.mp3",
      "date": "2026年3月6日",
      "startTime": "03:00:29.26",
      "endTime": "03:01:00.49",
      "personTag": "观众关系纠纷止损",
      "lastPosition": 0,
      "subtitleJsonPath": "/home/duino/ws/ququ/process_youtube/data/03_transcripts/曲曲2026/002 - 曲曲現場直播 2026年3月6日 ｜ 曲曲麥肯錫/22_观众关系纠纷止损_评论.json"
    },
    {
      "id": "002-item-23",
      "filename": "002_23_23_25岁硕士咨询情感纠缠_连麦.mp3",
      "filepath": "/audios/single/002_23_23_25岁硕士咨询情感纠缠_连麦.mp3",
      "date": "2026年3月6日",
      "startTime": "03:01:00.49",
      "endTime": "03:26:53.03",
      "personTag": "25岁硕士咨询情感纠缠",
      "lastPosition": 0,
      "subtitleJsonPath": "/home/duino/ws/ququ/process_youtube/data/03_transcripts/曲曲2026/002 - 曲曲現場直播 2026年3月6日 ｜ 曲曲麥肯錫/23_25岁硕士咨询情感纠缠_连麦.json"
    },
    {
      "id": "002-item-24",
      "filename": "002_24_24_25岁硕士咨询情感纠缠_评论.mp3",
      "filepath": "/audios/single/002_24_24_25岁硕士咨询情感纠缠_评论.mp3",
      "date": "2026年3月6日",
      "startTime": "03:26:52.94",
      "endTime": "03:30:49.45",
      "personTag": "25岁硕士咨询情感纠缠",
      "lastPosition": 0,
      "subtitleJsonPath": "/home/duino/ws/ququ/process_youtube/data/03_transcripts/曲曲2026/002 - 曲曲現場直播 2026年3月6日 ｜ 曲曲麥肯錫/24_25岁硕士咨询情感纠缠_评论.json"
    },
    {
      "id": "002-item-25",
      "filename": "002_25_25_观众回头草决策_连麦.mp3",
      "filepath": "/audios/single/002_25_25_观众回头草决策_连麦.mp3",
      "date": "2026年3月6日",
      "startTime": "03:30:49.45",
      "endTime": "03:47:47.40",
      "personTag": "观众回头草决策",
      "lastPosition": 0,
      "subtitleJsonPath": "/home/duino/ws/ququ/process_youtube/data/03_transcripts/曲曲2026/002 - 曲曲現場直播 2026年3月6日 ｜ 曲曲麥肯錫/25_观众回头草决策_连麦.json"
    },
    {
      "id": "002-item-26",
      "filename": "002_26_26_观众回头草决策_评论.mp3",
      "filepath": "/audios/single/002_26_26_观众回头草决策_评论.mp3",
      "date": "2026年3月6日",
      "startTime": "03:47:47.20",
      "endTime": "03:48:17.42",
      "personTag": "观众回头草决策",
      "lastPosition": 0,
      "subtitleJsonPath": "/home/duino/ws/ququ/process_youtube/data/03_transcripts/曲曲2026/002 - 曲曲現場直播 2026年3月6日 ｜ 曲曲麥肯錫/26_观众回头草决策_评论.json"
    },
    {
      "id": "002-item-27",
      "filename": "002_27_27_观众复杂关系处理_连麦.mp3",
      "filepath": "/audios/single/002_27_27_观众复杂关系处理_连麦.mp3",
      "date": "2026年3月6日",
      "startTime": "03:48:17.42",
      "endTime": "03:56:39.54",
      "personTag": "观众复杂关系处理",
      "lastPosition": 0,
      "subtitleJsonPath": "/home/duino/ws/ququ/process_youtube/data/03_transcripts/曲曲2026/002 - 曲曲現場直播 2026年3月6日 ｜ 曲曲麥肯錫/27_观众复杂关系处理_连麦.json"
    },
    {
      "id": "002-item-28",
      "filename": "002_28_28_观众复杂关系处理_评论.mp3",
      "filepath": "/audios/single/002_28_28_观众复杂关系处理_评论.mp3",
      "date": "2026年3月6日",
      "startTime": "03:56:39.54",
      "endTime": "03:57:12.35",
      "personTag": "观众复杂关系处理",
      "lastPosition": 0,
      "subtitleJsonPath": "/home/duino/ws/ququ/process_youtube/data/03_transcripts/曲曲2026/002 - 曲曲現場直播 2026年3月6日 ｜ 曲曲麥肯錫/28_观众复杂关系处理_评论.json"
    },
    {
      "id": "002-item-29",
      "filename": "002_29_29_女观众索取感与上嫁_连麦.mp3",
      "filepath": "/audios/single/002_29_29_女观众索取感与上嫁_连麦.mp3",
      "date": "2026年3月6日",
      "startTime": "03:57:12.35",
      "endTime": "04:08:19.95",
      "personTag": "女观众索取感与上嫁",
      "lastPosition": 0,
      "subtitleJsonPath": "/home/duino/ws/ququ/process_youtube/data/03_transcripts/曲曲2026/002 - 曲曲現場直播 2026年3月6日 ｜ 曲曲麥肯錫/29_女观众索取感与上嫁_连麦.json"
    }
  ]
}